perceval/_version.py
perceval/archive.py
perceval/backend.py
perceval/backends/core/__init__.py
perceval/backends/core/askbot.py
perceval/backends/core/bugzilla.py
perceval/backends/core/bugzillarest.py
perceval/backends/core/confluence.py
perceval/backends/core/discourse.py
perceval/backends/core/dockerhub.py
perceval/backends/core/gerrit.py
perceval/backends/core/git.py
perceval/backends/core/github.py
perceval/backends/core/githubql.py
perceval/backends/core/gitlab.py
perceval/backends/core/gitter.py
perceval/backends/core/googlehits.py
perceval/backends/core/groupsio.py
perceval/backends/core/hyperkitty.py
perceval/backends/core/jenkins.py
perceval/backends/core/jira.py
perceval/backends/core/launchpad.py
perceval/backends/core/mattermost.py
perceval/backends/core/mbox.py
perceval/backends/core/mediawiki.py
perceval/backends/core/meetup.py
perceval/backends/core/nntp.py
perceval/backends/core/pagure.py
perceval/backends/core/phabricator.py
perceval/backends/core/pipermail.py
perceval/backends/core/redmine.py
perceval/backends/core/rocketchat.py
perceval/backends/core/rss.py
perceval/backends/core/slack.py
perceval/backends/core/stackexchange.py
perceval/backends/core/supybot.py
perceval/backends/core/telegram.py
perceval/backends/core/twitter.py
perceval/client.py
perceval/errors.py
perceval/perceval.py
perceval/utils.py
perceval-1.4.5.dist-info/METADATA
perceval-1.4.5.dist-info/WHEEL
perceval-1.4.5.dist-info/entry_points.txt
perceval-1.4.5.dist-info/licenses/AUTHORS
perceval-1.4.5.dist-info/licenses/LICENSE
perceval-1.4.5.dist-info/RECORD
