Metadata-Version: 2.4
Name: perceval
Version: 1.4.5
Summary: Send Sir Perceval on a quest to fetch and gather data from software repositories.
License: GPL-3.0+
License-File: AUTHORS
License-File: LICENSE
Keywords: development,grimoirelab
Author: GrimoireLab Developers
Requires-Python: >=3.10,<4.0
Classifier: Development Status :: 5 - Production/Stable
Classifier: Intended Audience :: Developers
Classifier: Intended Audience :: Science/Research
Classifier: License :: OSI Approved :: GNU General Public License v3 or later (GPLv3+)
Classifier: Programming Language :: Python :: 3
Classifier: Programming Language :: Python :: 3.10
Classifier: Programming Language :: Python :: 3.11
Classifier: Programming Language :: Python :: 3.12
Classifier: Programming Language :: Python :: 3.13
Classifier: Programming Language :: Python :: 3.14
Classifier: Topic :: Software Development
Provides-Extra: docs
Requires-Dist: PyJWT[crypto] (>=2.4.0,<3.0.0)
Requires-Dist: beautifulsoup4 (>=4.3.2,<5.0.0)
Requires-Dist: dulwich (>=0.21.5,<0.23.0)
Requires-Dist: feedparser (>=6.0.8,<7.0.0)
Requires-Dist: furo (>=2023.3.27,<2024.0.0) ; extra == "docs"
Requires-Dist: grimoirelab-toolkit (>=0.3)
Requires-Dist: myst-parser (>=1.0.0,<2.0.0) ; extra == "docs"
Requires-Dist: python-dateutil (>=2.6.0,<3.0.0)
Requires-Dist: requests (>=2.7.0,<3.0.0)
Requires-Dist: urllib3 (>=2.2,<3.0)
Project-URL: Bug Tracker, https://github.com/chaoss/grimoirelab-perceval/issues
Project-URL: Homepage, https://chaoss.github.io/grimoirelab/
Project-URL: Repository, https://github.com/chaoss/grimoirelab-perceval
